crfm_helm-0.5.11.dist-info/licenses/LICENSE
helm/__init__.py
helm/py.typed
helm/benchmark/__init__.py
helm/benchmark/annotation_executor.py
helm/benchmark/config_registry.py
helm/benchmark/data_preprocessor.py
helm/benchmark/executor.py
helm/benchmark/huggingface_registration.py
helm/benchmark/model_deployment_registry.py
helm/benchmark/model_metadata_registry.py
helm/benchmark/multi_gpu_runner.py
helm/benchmark/reeval_run.py
helm/benchmark/reeval_runner.py
helm/benchmark/run.py
helm/benchmark/run_expander.py
helm/benchmark/run_spec.py
helm/benchmark/run_spec_factory.py
helm/benchmark/runner.py
helm/benchmark/runner_config_registry.py
helm/benchmark/server.py
helm/benchmark/slurm_jobs.py
helm/benchmark/slurm_runner.py
helm/benchmark/test_data_preprocessor.py
helm/benchmark/test_run_expander.py
helm/benchmark/tokenizer_config_registry.py
helm/benchmark/adaptation/__init__.py
helm/benchmark/adaptation/adapter_spec.py
helm/benchmark/adaptation/common_adapter_specs.py
helm/benchmark/adaptation/prompt.py
helm/benchmark/adaptation/request_state.py
helm/benchmark/adaptation/scenario_state.py
helm/benchmark/adaptation/adapters/__init__.py
helm/benchmark/adaptation/adapters/adapter.py
helm/benchmark/adaptation/adapters/adapter_factory.py
helm/benchmark/adaptation/adapters/binary_ranking_adapter.py
helm/benchmark/adaptation/adapters/chat_adapter.py
helm/benchmark/adaptation/adapters/ehr_instruction_adapter.py
helm/benchmark/adaptation/adapters/generation_adapter.py
helm/benchmark/adaptation/adapters/in_context_learning_adapter.py
helm/benchmark/adaptation/adapters/language_modeling_adapter.py
helm/benchmark/adaptation/adapters/multiple_choice_calibrated_adapter.py
helm/benchmark/adaptation/adapters/multiple_choice_joint_adapter.py
helm/benchmark/adaptation/adapters/multiple_choice_joint_chain_of_thought_adapter.py
helm/benchmark/adaptation/adapters/multiple_choice_separate_adapter.py
helm/benchmark/adaptation/adapters/test_adapter.py
helm/benchmark/adaptation/adapters/test_generation_adapter.py
crfm_helm-0.5.11.dist-info/METADATA
crfm_helm-0.5.11.dist-info/WHEEL
crfm_helm-0.5.11.dist-info/entry_points.txt
crfm_helm-0.5.11.dist-info/top_level.txt
crfm_helm-0.5.11.dist-info/RECORD
