Metadata-Version: 2.4
Name: crfm-helm
Version: 0.5.11
Summary: Framework for evaluation of foundation models
Author-email: Stanford CRFM <contact-crfm@stanford.edu>
License: Apache License 2.0
Project-URL: Homepage, https://github.com/stanford-crfm/helm
Keywords: language,models,benchmarking
Classifier: Programming Language :: Python :: 3
Classifier: Programming Language :: Python :: 3 :: Only
Classifier: License :: OSI Approved :: Apache Software License
Requires-Python: >=3.10
License-File: LICENSE
Requires-Dist: cattrs~=22.2
Requires-Dist: colorlog~=6.9
Requires-Dist: dacite~=1.6
Requires-Dist: Mako~=1.2
Requires-Dist: numpy<3,>=1.26
Requires-Dist: pandas~=2.0
Requires-Dist: pyhocon~=0.3.59
Requires-Dist: retrying~=1.3
Requires-Dist: spacy~=3.5
Requires-Dist: tqdm~=4.64
Requires-Dist: zstandard~=0.18.0
Requires-Dist: sqlitedict<3.0,>=2.1.0
Requires-Dist: bottle~=0.12.23
Requires-Dist: datasets~=3.1
Requires-Dist: pyarrow>=11.0.0
Requires-Dist: pyarrow-hotfix~=0.6
Requires-Dist: nltk!=3.9.0,~=3.7
Requires-Dist: rouge-score~=0.1.2
Requires-Dist: scipy>=1.10
Requires-Dist: uncertainty-calibration~=0.1.4
Requires-Dist: scikit-learn>=1.1
Requires-Dist: transformers<4.53.0,~=4.40
Requires-Dist: torch<3.0.0,>=1.13.1
Requires-Dist: torchvision<3.0.0,>=0.14.1
Provides-Extra: proxy-server
Requires-Dist: gunicorn>=20.1; extra == "proxy-server"
Provides-Extra: human-evaluation
Requires-Dist: scaleapi~=2.13; extra == "human-evaluation"
Requires-Dist: surge-api~=1.1; extra == "human-evaluation"
Provides-Extra: dspy
Requires-Dist: dspy~=3.0.3; extra == "dspy"
Requires-Dist: fastapi~=0.118.0; extra == "dspy"
Requires-Dist: apscheduler~=3.11.0; extra == "dspy"
Requires-Dist: cryptography~=43.0.3; extra == "dspy"
Requires-Dist: python-multipart~=0.0.20; extra == "dspy"
Requires-Dist: email-validator~=2.3.0; extra == "dspy"
Requires-Dist: fastapi_sso~=0.18.0; extra == "dspy"
Provides-Extra: scenarios
Requires-Dist: gdown~=5.1; extra == "scenarios"
Requires-Dist: xlrd~=2.0; extra == "scenarios"
Provides-Extra: metrics
Requires-Dist: google-api-python-client~=2.64; extra == "metrics"
Requires-Dist: numba~=0.56; extra == "metrics"
Requires-Dist: sacrebleu~=2.2; extra == "metrics"
Requires-Dist: langdetect~=1.0; extra == "metrics"
Requires-Dist: immutabledict~=4.2; extra == "metrics"
Requires-Dist: gradio_client~=1.3; extra == "metrics"
Provides-Extra: ranking
Requires-Dist: pytrec_eval==0.5; extra == "ranking"
Provides-Extra: plots
Requires-Dist: colorcet~=3.0; extra == "plots"
Requires-Dist: matplotlib>=3.6.0; extra == "plots"
Requires-Dist: seaborn>=0.11.0; extra == "plots"
Provides-Extra: decodingtrust
Requires-Dist: fairlearn~=0.9.0; extra == "decodingtrust"
Provides-Extra: slurm
Requires-Dist: simple-slurm~=0.2.6; extra == "slurm"
Provides-Extra: cleva
Requires-Dist: unidecode~=1.3; extra == "cleva"
Requires-Dist: pypinyin~=0.49.0; extra == "cleva"
Requires-Dist: jieba~=0.42.1; extra == "cleva"
Requires-Dist: opencc~=1.1; extra == "cleva"
Requires-Dist: langdetect~=1.0; extra == "cleva"
Provides-Extra: images
Requires-Dist: crfm-helm[accelerate]; extra == "images"
Requires-Dist: pillow>=10.2; extra == "images"
Provides-Extra: mongo
Requires-Dist: pymongo~=4.2; extra == "mongo"
Provides-Extra: unitxt
Requires-Dist: evaluate~=0.4.1; extra == "unitxt"
Provides-Extra: seahelm
Requires-Dist: pythainlp==5.0.0; extra == "seahelm"
Requires-Dist: pyonmttok==1.37.0; extra == "seahelm"
Requires-Dist: sacrebleu~=2.2; extra == "seahelm"
Requires-Dist: python-crfsuite~=0.9.11; extra == "seahelm"
Provides-Extra: accelerate
Requires-Dist: accelerate~=0.25; extra == "accelerate"
Provides-Extra: aleph-alpha
Requires-Dist: aleph-alpha-client~=2.14; extra == "aleph-alpha"
Requires-Dist: tokenizers>=0.13.3; extra == "aleph-alpha"
Provides-Extra: allenai
Requires-Dist: ai2-olmo~=0.2; extra == "allenai"
Provides-Extra: amazon
Requires-Dist: boto3~=1.34; extra == "amazon"
Requires-Dist: awscli~=1.33; extra == "amazon"
Requires-Dist: botocore~=1.34; extra == "amazon"
Provides-Extra: anthropic
Requires-Dist: anthropic~=0.41; extra == "anthropic"
Requires-Dist: websocket-client~=1.3; extra == "anthropic"
Provides-Extra: cohere
Requires-Dist: cohere~=5.3; extra == "cohere"
Provides-Extra: writer
Requires-Dist: writerai~=4.0; extra == "writer"
Provides-Extra: mistral
Requires-Dist: mistralai~=1.1; extra == "mistral"
Provides-Extra: openai
Requires-Dist: openai~=1.70; extra == "openai"
Requires-Dist: tiktoken~=0.7; extra == "openai"
Requires-Dist: pydantic~=2.0; extra == "openai"
Provides-Extra: google
Requires-Dist: google-cloud-aiplatform~=1.48; extra == "google"
Requires-Dist: google-genai~=1.48; extra == "google"
Provides-Extra: together
Requires-Dist: together~=1.1; extra == "together"
Provides-Extra: yandex
Requires-Dist: sentencepiece~=0.2.0; extra == "yandex"
Provides-Extra: models
Requires-Dist: crfm-helm[ai21]; extra == "models"
Requires-Dist: crfm-helm[accelerate]; extra == "models"
Requires-Dist: crfm-helm[aleph-alpha]; extra == "models"
Requires-Dist: crfm-helm[allenai]; extra == "models"
Requires-Dist: crfm-helm[amazon]; extra == "models"
Requires-Dist: crfm-helm[anthropic]; extra == "models"
Requires-Dist: crfm-helm[cohere]; extra == "models"
Requires-Dist: crfm-helm[google]; extra == "models"
Requires-Dist: crfm-helm[mistral]; extra == "models"
Requires-Dist: crfm-helm[openai]; extra == "models"
Requires-Dist: crfm-helm[reka]; extra == "models"
Requires-Dist: crfm-helm[together]; extra == "models"
Requires-Dist: crfm-helm[yandex]; extra == "models"
Requires-Dist: crfm-helm[writer]; extra == "models"
Provides-Extra: reka
Requires-Dist: reka-api~=2.0; extra == "reka"
Provides-Extra: vlm
Requires-Dist: crfm-helm[openai]; extra == "vlm"
Requires-Dist: einops~=0.7.0; extra == "vlm"
Requires-Dist: einops-exts~=0.0.4; extra == "vlm"
Requires-Dist: open-clip-torch~=2.24; extra == "vlm"
Requires-Dist: torch~=2.1; extra == "vlm"
Requires-Dist: transformers_stream_generator~=0.0.4; extra == "vlm"
Requires-Dist: scipy~=1.10; extra == "vlm"
Requires-Dist: torchvision<3.0.0,>=0.14.1; extra == "vlm"
Requires-Dist: crfm-helm[reka]; extra == "vlm"
Requires-Dist: crfm-helm[images]; extra == "vlm"
Requires-Dist: crfm-helm[image2struct]; extra == "vlm"
Requires-Dist: pycocoevalcap~=1.2; extra == "vlm"
Requires-Dist: transformers~=4.45; extra == "vlm"
Requires-Dist: qwen-vl-utils~=0.0.8; extra == "vlm"
Provides-Extra: ibm-enterprise-scenarios
Requires-Dist: openpyxl~=3.1; extra == "ibm-enterprise-scenarios"
Provides-Extra: ibm
Requires-Dist: ibm-watsonx-ai~=1.2; extra == "ibm"
Provides-Extra: image2struct
Requires-Dist: crfm-helm[images]; extra == "image2struct"
Requires-Dist: latex~=0.7.0; extra == "image2struct"
Requires-Dist: pdf2image~=1.16; extra == "image2struct"
Requires-Dist: selenium~=4.17; extra == "image2struct"
Requires-Dist: html2text~=2024.2.26; extra == "image2struct"
Requires-Dist: opencv-python-headless<=4.11.0.86,>=4.7.0.68; extra == "image2struct"
Requires-Dist: lpips~=0.1.4; extra == "image2struct"
Requires-Dist: imagehash~=4.3; extra == "image2struct"
Provides-Extra: heim
Requires-Dist: gdown~=5.1; extra == "heim"
Requires-Dist: diffusers~=0.34.0; extra == "heim"
Requires-Dist: icetk~=0.0.4; extra == "heim"
Requires-Dist: jax~=0.6.2; python_version >= "3.10" and extra == "heim"
Requires-Dist: jax~=0.4.30; python_version < "3.10" and extra == "heim"
Requires-Dist: jaxlib~=0.6.2; python_version >= "3.10" and extra == "heim"
Requires-Dist: jaxlib~=0.4.30; python_version < "3.10" and extra == "heim"
Requires-Dist: crfm-helm[openai]; extra == "heim"
Requires-Dist: einops~=0.7.0; extra == "heim"
Requires-Dist: omegaconf~=2.3; extra == "heim"
Requires-Dist: pytorch-lightning~=2.0; extra == "heim"
Requires-Dist: flax~=0.10.7; python_version >= "3.10" and extra == "heim"
Requires-Dist: flax~=0.8.5; python_version < "3.10" and extra == "heim"
Requires-Dist: ftfy~=6.1; extra == "heim"
Requires-Dist: Unidecode~=1.3; extra == "heim"
Requires-Dist: wandb~=0.16; extra == "heim"
Requires-Dist: google-cloud-translate~=3.11; extra == "heim"
Requires-Dist: autokeras~=1.0; extra == "heim"
Requires-Dist: clip-anytorch~=2.5; extra == "heim"
Requires-Dist: google-cloud-storage~=2.9; extra == "heim"
Requires-Dist: lpips~=0.1.4; extra == "heim"
Requires-Dist: multilingual-clip~=1.0; extra == "heim"
Requires-Dist: NudeNet~=2.0; extra == "heim"
Requires-Dist: numpy>=1.26; extra == "heim"
Requires-Dist: opencv-python<4.8.2.0,>=4.7.0.68; python_version >= "3.10" and extra == "heim"
Requires-Dist: opencv-python-headless<=4.11.0.86,>=4.7.0.68; python_version < "3.10" and extra == "heim"
Requires-Dist: pytorch-fid~=0.3.0; extra == "heim"
Requires-Dist: tensorflow~=2.11; extra == "heim"
Requires-Dist: timm~=0.6.12; extra == "heim"
Requires-Dist: torch-fidelity~=0.3.0; extra == "heim"
Requires-Dist: torchmetrics~=0.11.1; extra == "heim"
Requires-Dist: scikit-image==0.*,>=0.22; extra == "heim"
Requires-Dist: crfm-helm[images]; extra == "heim"
Provides-Extra: medhelm
Requires-Dist: accelerate~=0.25; extra == "medhelm"
Requires-Dist: crfm-helm[openai]; extra == "medhelm"
Requires-Dist: crfm-helm[yandex]; extra == "medhelm"
Requires-Dist: crfm-helm[scenarios]; extra == "medhelm"
Requires-Dist: bert_score~=0.3.13; extra == "medhelm"
Requires-Dist: lxml~=5.3; extra == "medhelm"
Requires-Dist: openpyxl~=3.1; extra == "medhelm"
Requires-Dist: python-docx~=1.1; extra == "medhelm"
Requires-Dist: transformers<4.50,~=4.45; extra == "medhelm"
Provides-Extra: audiolm
Requires-Dist: crfm-helm[openai]; extra == "audiolm"
Requires-Dist: crfm-helm[google]; extra == "audiolm"
Requires-Dist: pydub~=0.25.1; extra == "audiolm"
Requires-Dist: ffmpeg-python~=0.2.0; extra == "audiolm"
Requires-Dist: soundfile~=0.12; extra == "audiolm"
Requires-Dist: librosa~=0.10; extra == "audiolm"
Requires-Dist: einops~=0.7.0; extra == "audiolm"
Requires-Dist: openai-whisper==20240930; extra == "audiolm"
Requires-Dist: transformers~=4.48; extra == "audiolm"
Requires-Dist: transformers_stream_generator~=0.0.4; extra == "audiolm"
Requires-Dist: av~=14.3; extra == "audiolm"
Requires-Dist: scipy~=1.10; extra == "audiolm"
Requires-Dist: torchvision<3.0.0,>=0.14.1; extra == "audiolm"
Requires-Dist: flash-attn~=2.7; extra == "audiolm"
Requires-Dist: pycocoevalcap~=1.2; extra == "audiolm"
Requires-Dist: jiwer~=3.0; extra == "audiolm"
Requires-Dist: rapidfuzz~=3.10; extra == "audiolm"
Requires-Dist: jieba~=0.42.1; extra == "audiolm"
Provides-Extra: codeinsights
Requires-Dist: clang~=20.1; extra == "codeinsights"
Requires-Dist: Levenshtein~=0.27; extra == "codeinsights"
Provides-Extra: lmkt
Requires-Dist: sentence_transformers~=4.1; extra == "lmkt"
Provides-Extra: all
Requires-Dist: crfm-helm[proxy-server]; extra == "all"
Requires-Dist: crfm-helm[human-evaluation]; extra == "all"
Requires-Dist: crfm-helm[scenarios]; extra == "all"
Requires-Dist: crfm-helm[metrics]; extra == "all"
Requires-Dist: crfm-helm[plots]; extra == "all"
Requires-Dist: crfm-helm[decodingtrust]; extra == "all"
Requires-Dist: crfm-helm[slurm]; extra == "all"
Requires-Dist: crfm-helm[cleva]; extra == "all"
Requires-Dist: crfm-helm[images]; extra == "all"
Requires-Dist: crfm-helm[models]; extra == "all"
Requires-Dist: crfm-helm[mongo]; extra == "all"
Requires-Dist: crfm-helm[heim]; extra == "all"
Requires-Dist: crfm-helm[vlm]; extra == "all"
Requires-Dist: crfm-helm[codeinsights]; extra == "all"
Requires-Dist: crfm-helm[lmkt]; extra == "all"
Provides-Extra: ci
Requires-Dist: crfm-helm[metrics]; extra == "ci"
Requires-Dist: crfm-helm[openai]; extra == "ci"
Requires-Dist: crfm-helm[plots]; extra == "ci"
Requires-Dist: crfm-helm[together]; extra == "ci"
Requires-Dist: crfm-helm[yandex]; extra == "ci"
Requires-Dist: crfm-helm[cohere]; extra == "ci"
Requires-Dist: crfm-helm[proxy-server]; extra == "ci"
Dynamic: license-file
